cloner/__init__.py
cloner/ssm_cloner.py
ssm_cloner-0.0.1.dist-info/LICENSE
ssm_cloner-0.0.1.dist-info/METADATA
ssm_cloner-0.0.1.dist-info/WHEEL
ssm_cloner-0.0.1.dist-info/top_level.txt
ssm_cloner-0.0.1.dist-info/RECORD
