Metadata-Version: 2.1
Name: ssm-cloner
Version: 0.0.1
Summary: (Not to be used as of now) This package is used to simplify the process of cloning the SSM documents across the AWS regions.
Home-page: https://github.com/lovepurohit/ssm-cloner
Author: Love Purohit
Author-email: lvpurohit1@gmail.com
License: UNKNOWN
Project-URL: Bug Tracker, https://github.com/lovepurohit/ssm-cloner/issues
Platform: UNKNOWN
Classifier: Programming Language :: Python :: 3
Classifier: License :: OSI Approved :: MIT License
Classifier: Operating System :: OS Independent
Requires-Python: >=3.6
Requires-Dist: boto3
